geistt_lab_rti_client/__init__.py
geistt_lab_rti_client/constants.py
geistt_lab_rti_client/rticlient.py
geistt_lab_rti_client/rtiruntimecontrol.py
geistt_lab_rti_client/rtisocketclusterclient.py
geistt_lab_rti_client/generated/Channels_pb2.py
geistt_lab_rti_client/generated/Clients_pb2.py
geistt_lab_rti_client/generated/Color_pb2.py
geistt_lab_rti_client/generated/Commands_pb2.py
geistt_lab_rti_client/generated/EntityCategory_pb2.py
geistt_lab_rti_client/generated/EntityDomain_pb2.py
geistt_lab_rti_client/generated/EntityOperation_pb2.py
geistt_lab_rti_client/generated/EntityPosition_pb2.py
geistt_lab_rti_client/generated/GeometryOperation_pb2.py
geistt_lab_rti_client/generated/IdMessage_pb2.py
geistt_lab_rti_client/generated/Injectables_pb2.py
geistt_lab_rti_client/generated/Injections_pb2.py
geistt_lab_rti_client/generated/LVCCategory_pb2.py
geistt_lab_rti_client/generated/LaunchConfigurations_pb2.py
geistt_lab_rti_client/generated/LaunchEvent_pb2.py
geistt_lab_rti_client/generated/Logs_pb2.py
geistt_lab_rti_client/generated/MeasurementBundle_pb2.py
geistt_lab_rti_client/generated/Measurement_pb2.py
geistt_lab_rti_client/generated/Measures_pb2.py
geistt_lab_rti_client/generated/MessageBundle_pb2.py
geistt_lab_rti_client/generated/Parameter_pb2.py
geistt_lab_rti_client/generated/RuntimeControl_pb2.py
geistt_lab_rti_client/generated/RuntimeState_pb2.py
geistt_lab_rti_client/generated/Scenarios_pb2.py
geistt_lab_rti_client/proto/__init__.py
geistt_lab_rti_client-1.12.4.dist-info/LICENSE.txt
geistt_lab_rti_client-1.12.4.dist-info/METADATA
geistt_lab_rti_client-1.12.4.dist-info/WHEEL
geistt_lab_rti_client-1.12.4.dist-info/top_level.txt
geistt_lab_rti_client-1.12.4.dist-info/RECORD
