Metadata-Version: 2.1
Name: geistt-lab-rti-client
Version: 1.12.4
Summary: GEISTT Lab RTI Client
Home-page: https://gitlab.com/geistt/lab/rti
Author: GEISTT AB
Author-email: packages@geistt.com
License: Apache license 2.0
Keywords: RTI
Classifier: Development Status :: 3 - Alpha
Classifier: Intended Audience :: Developers
Classifier: License :: OSI Approved :: Apache Software License
Classifier: Programming Language :: Python :: 3
Classifier: Programming Language :: Python :: 3.6
Classifier: Programming Language :: Python :: 3.7
License-File: LICENSE.txt
Requires-Dist: protobuf
Requires-Dist: emitter.py
Requires-Dist: websocket-client
